{
	"color_scheme": "Packages/Color Scheme - Default/Sixteen.sublime-color-scheme",
	"default_line_ending": "unix",
	"draw_white_space": "all",
	"ensure_newline_at_eof_on_save": true,
	"font_size": 15,
	"highlight_line": true,
	"highlight_modified_tabs": true,
	"ignored_packages":
	[
		"Markdown",
		"Vintage"
	],
	"mde.detect_heading_style": false,
	"mde.match_heading_hashes": false,
	"tab_size": 2,
	"theme": "Default.sublime-theme",
	"translate_tabs_to_spaces": false,
	"trim_trailing_white_space_on_save": true
}
